pytrisk/__main__.py
pytrisk/config.py
pytrisk/gui.py
pytrisk/locale.py
pytrisk/logging.py
pytrisk/maps.py
pytrisk/gui/icons/close.png
pytrisk/gui/icons/exit.png
pytrisk/gui/icons/next.png
pytrisk/gui/icons/redo.png
pytrisk/gui/icons/stop.png
pytrisk/locale/fr/LC_MESSAGES/pytrisk.mo
pytrisk/maps/ameroki/background.jpg
pytrisk/maps/ameroki/connections.csv
pytrisk/maps/ameroki/continents.csv
pytrisk/maps/ameroki/countries.csv
pytrisk/maps/ameroki/info.yaml
pytrisk/maps/france/background.jpg
pytrisk/maps/france/connections.csv
pytrisk/maps/france/continents.csv
pytrisk/maps/france/countries.csv
pytrisk/maps/france/info.yaml
pytrisk/maps/godstorm/background.jpg
pytrisk/maps/godstorm/connections.csv
pytrisk/maps/godstorm/continents.csv
pytrisk/maps/godstorm/countries.csv
pytrisk/maps/godstorm/info.yaml
pytrisk/maps/lotr/background.jpg
pytrisk/maps/lotr/connections.csv
pytrisk/maps/lotr/continents.csv
pytrisk/maps/lotr/countries.csv
pytrisk/maps/lotr/info.yaml
pytrisk/maps/risk/background.jpg
pytrisk/maps/risk/connections.csv
pytrisk/maps/risk/continents.csv
pytrisk/maps/risk/countries.csv
pytrisk/maps/risk/info.yaml
pytrisk/maps/risk2210/background.jpg
pytrisk/maps/risk2210/connections.csv
pytrisk/maps/risk2210/continents.csv
pytrisk/maps/risk2210/countries.csv
pytrisk/maps/risk2210/info.yaml
pytrisk/maps/roman_empire/background.png
pytrisk/maps/roman_empire/connections.csv
pytrisk/maps/roman_empire/continents.csv
pytrisk/maps/roman_empire/countries.csv
pytrisk/maps/roman_empire/info.yaml
pytrisk-0.1.1.dist-info/LICENSE
pytrisk-0.1.1.dist-info/METADATA
pytrisk-0.1.1.dist-info/WHEEL
pytrisk-0.1.1.dist-info/entry_points.txt
pytrisk-0.1.1.dist-info/top_level.txt
pytrisk-0.1.1.dist-info/RECORD
