Metadata-Version: 2.1
Name: pytrisk
Version: 0.1.1
Summary: classical Risk game
Author-email: Jerome Quelin <jquelin@gmail.com>
Project-URL: Homepage, https://github.com/jquelin/pytrisk
Project-URL: Bug Tracker, https://github.com/jquelin/pytrisk/issues
Classifier: Programming Language :: Python :: 3
Classifier: License :: OSI Approved :: GNU General Public License v3 or later (GPLv3+)
Classifier: Operating System :: OS Independent
Requires-Python: >=3.7
License-File: LICENSE
Requires-Dist: appdirs
Requires-Dist: pathlib
